{
  "label": "US · S&P 500 (sample 40)",
  "asOf": "2026-06-30",
  "source": "Stooq (daily % change) + local mcap cache (if available); constituents via Wikipedia/CSV",
  "items": [
    {
      "ticker": "MMM",
      "name": "3M",
      "sector": "Industrials",
      "pct": -0.9633570416276216,
      "mcap_usd_b": 1.0
    },
    {
      "ticker": "AOS",
      "name": "A. O. Smith",
      "sector": "Industrials",
      "pct": -0.06481029607291466,
      "mcap_usd_b": 1.0
    },
    {
      "ticker": "ABT",
      "name": "Abbott Laboratories",
      "sector": "Health Care",
      "pct": -1.4980913949883878,
      "mcap_usd_b": 1.0
    },
    {
      "ticker": "ABBV",
      "name": "AbbVie",
      "sector": "Health Care",
      "pct": 0.37891905741098686,
      "mcap_usd_b": 1.0
    },
    {
      "ticker": "ACN",
      "name": "Accenture",
      "sector": "Information Technology",
      "pct": -3.2873298218478952,
      "mcap_usd_b": 1.0
    },
    {
      "ticker": "ADBE",
      "name": "Adobe Inc.",
      "sector": "Information Technology",
      "pct": 1.8250860880078212,
      "mcap_usd_b": 1.0
    },
    {
      "ticker": "AMD",
      "name": "Advanced Micro Devices",
      "sector": "Information Technology",
      "pct": 3.43379204680041,
      "mcap_usd_b": 1.0
    },
    {
      "ticker": "AES",
      "name": "AES Corporation",
      "sector": "Utilities",
      "pct": -0.2726650418882093,
      "mcap_usd_b": 1.0
    },
    {
      "ticker": "AFL",
      "name": "Aflac",
      "sector": "Financials",
      "pct": -0.0582602529631604,
      "mcap_usd_b": 1.0
    },
    {
      "ticker": "A",
      "name": "Agilent Technologies",
      "sector": "Health Care",
      "pct": -2.338058087063166,
      "mcap_usd_b": 1.0
    },
    {
      "ticker": "APD",
      "name": "Air Products",
      "sector": "Materials",
      "pct": -2.3182988024440854,
      "mcap_usd_b": 1.0
    },
    {
      "ticker": "ABNB",
      "name": "Airbnb",
      "sector": "Consumer Discretionary",
      "pct": 1.106073534869001,
      "mcap_usd_b": 1.0
    },
    {
      "ticker": "AKAM",
      "name": "Akamai Technologies",
      "sector": "Information Technology",
      "pct": 0.45017400662812346,
      "mcap_usd_b": 1.0
    },
    {
      "ticker": "ALB",
      "name": "Albemarle Corporation",
      "sector": "Materials",
      "pct": -2.9768106345430922,
      "mcap_usd_b": 1.0
    },
    {
      "ticker": "ARE",
      "name": "Alexandria Real Estate Equities",
      "sector": "Real Estate",
      "pct": 0.670045135287034,
      "mcap_usd_b": 1.0
    },
    {
      "ticker": "ALGN",
      "name": "Align Technology",
      "sector": "Health Care",
      "pct": -2.802219472757206,
      "mcap_usd_b": 1.0
    },
    {
      "ticker": "ALLE",
      "name": "Allegion",
      "sector": "Industrials",
      "pct": -0.042955274854239445,
      "mcap_usd_b": 1.0
    },
    {
      "ticker": "LNT",
      "name": "Alliant Energy",
      "sector": "Utilities",
      "pct": -0.09061449168183966,
      "mcap_usd_b": 1.0
    },
    {
      "ticker": "ALL",
      "name": "Allstate",
      "sector": "Financials",
      "pct": 0.7387021693386231,
      "mcap_usd_b": 1.0
    },
    {
      "ticker": "GOOGL",
      "name": "Alphabet Inc. (Class A)",
      "sector": "Communication Services",
      "pct": 4.819342168436691,
      "mcap_usd_b": 1.0
    },
    {
      "ticker": "GOOG",
      "name": "Alphabet Inc. (Class C)",
      "sector": "Communication Services",
      "pct": 4.9568245889851426,
      "mcap_usd_b": 1.0
    },
    {
      "ticker": "MO",
      "name": "Altria",
      "sector": "Consumer Staples",
      "pct": 0.35235415775114465,
      "mcap_usd_b": 1.0
    },
    {
      "ticker": "AMZN",
      "name": "Amazon",
      "sector": "Consumer Discretionary",
      "pct": 3.2016832997017852,
      "mcap_usd_b": 1.0
    },
    {
      "ticker": "AMCR",
      "name": "Amcor",
      "sector": "Materials",
      "pct": -0.2091567630515323,
      "mcap_usd_b": 1.0
    },
    {
      "ticker": "AEE",
      "name": "Ameren",
      "sector": "Utilities",
      "pct": -3.1524707290011555,
      "mcap_usd_b": 1.0
    },
    {
      "ticker": "AEP",
      "name": "American Electric Power",
      "sector": "Utilities",
      "pct": -0.5191442843959226,
      "mcap_usd_b": 1.0
    },
    {
      "ticker": "AXP",
      "name": "American Express",
      "sector": "Financials",
      "pct": 0.15278515502135104,
      "mcap_usd_b": 1.0
    },
    {
      "ticker": "AIG",
      "name": "American International Group",
      "sector": "Financials",
      "pct": -0.5954703586865451,
      "mcap_usd_b": 1.0
    },
    {
      "ticker": "AMT",
      "name": "American Tower",
      "sector": "Real Estate",
      "pct": -3.940997957326142,
      "mcap_usd_b": 1.0
    },
    {
      "ticker": "AWK",
      "name": "American Water Works",
      "sector": "Utilities",
      "pct": -0.13565924458639467,
      "mcap_usd_b": 1.0
    },
    {
      "ticker": "AMP",
      "name": "Ameriprise Financial",
      "sector": "Financials",
      "pct": -1.3294735200480856,
      "mcap_usd_b": 1.0
    },
    {
      "ticker": "AME",
      "name": "Ametek",
      "sector": "Industrials",
      "pct": 0.08420214914308666,
      "mcap_usd_b": 1.0
    },
    {
      "ticker": "AMGN",
      "name": "Amgen",
      "sector": "Health Care",
      "pct": 0.6195410107703747,
      "mcap_usd_b": 1.0
    },
    {
      "ticker": "APH",
      "name": "Amphenol",
      "sector": "Information Technology",
      "pct": 1.6491552211769456,
      "mcap_usd_b": 1.0
    },
    {
      "ticker": "ADI",
      "name": "Analog Devices",
      "sector": "Information Technology",
      "pct": 1.2586893776570518,
      "mcap_usd_b": 1.0
    },
    {
      "ticker": "AON",
      "name": "Aon plc",
      "sector": "Financials",
      "pct": -0.3407451120717164,
      "mcap_usd_b": 1.0
    },
    {
      "ticker": "APA",
      "name": "APA Corporation",
      "sector": "Energy",
      "pct": -0.15146694820621365,
      "mcap_usd_b": 1.0
    },
    {
      "ticker": "APO",
      "name": "Apollo Global Management",
      "sector": "Financials",
      "pct": -2.9250139975427802,
      "mcap_usd_b": 1.0
    },
    {
      "ticker": "AAPL",
      "name": "Apple Inc.",
      "sector": "Information Technology",
      "pct": -0.7188697419469814,
      "mcap_usd_b": 1.0
    },
    {
      "ticker": "AMAT",
      "name": "Applied Materials",
      "sector": "Information Technology",
      "pct": 10.816154822321433,
      "mcap_usd_b": 1.0
    }
  ]
}