{
  "meta": {
    "generated_at": "2026-06-01T05:10:40.175237+00:00",
    "note": "GA4 Data API can lag hours; empty result right after install may be normal.",
    "property_id": "391730814",
    "range": "last_30_days_including_today"
  },
  "paths": {
    "/": {
      "views": 32
    },
    "/about/": {
      "views": 1
    },
    "/dev/markdown-hangul/part-1/": {
      "views": 1
    },
    "/dev/marp-editor/devlog-1/": {
      "views": 2
    },
    "/dev/marp-editor/devlog-2/": {
      "views": 1
    },
    "/dev/marp-editor/devlog-3/": {
      "views": 2
    },
    "/dev/tech/GA-N3160N-NAS/": {
      "views": 1
    },
    "/graph/": {
      "views": 1
    },
    "/investing/2026-04-08-korea/": {
      "views": 1
    },
    "/investing/2026-05-07-korea/": {
      "views": 1
    },
    "/investing/2026-05-07-us/": {
      "views": 1
    },
    "/investing/2026-05-08-us/": {
      "views": 4
    },
    "/macos/tidal-dl/": {
      "views": 4
    },
    "/tags/": {
      "views": 1
    },
    "/tags/hsi/": {
      "views": 1
    },
    "/tags/index/": {
      "views": 2
    },
    "/tags/markdown/": {
      "views": 1
    },
    "/tags/nextauth/": {
      "views": 1
    },
    "/tags/마크다운ㅎ글/": {
      "views": 1
    },
    "/tags/메가플래닝/": {
      "views": 1
    },
    "/theory/cohens-d/": {
      "views": 1
    },
    "/workbook/": {
      "views": 12
    },
    "/workbook/a/": {
      "views": 4
    },
    "/workbook/b/": {
      "views": 1
    },
    "/workbook/case-note/": {
      "views": 1
    },
    "/workbook/code-note/": {
      "views": 1
    }
  }
}
